fastDAS/__init__.py
fastDAS/das_lib.py
fastDAS/delay_and_sum.py
fastDAS/implementations.py
fastDAS/native_lib.py
fastDAS/py_lib.py
fastDAS/utils.py
fastDAS/bin/libdas.dll
fastDAS/bin/libdas.so
fastDAS/bin/libdas_cu.dll
fastDAS/bin/libdas_cu.so
fast_das-1.2.0.dist-info/LICENSE
fast_das-1.2.0.dist-info/METADATA
fast_das-1.2.0.dist-info/WHEEL
fast_das-1.2.0.dist-info/top_level.txt
fast_das-1.2.0.dist-info/RECORD
