Metadata-Version: 2.1
Name: fast-das
Version: 1.2.0
Summary: Parallel beamforming wrapper for native code
Author: talg
Project-URL: Source, https://github.com/talg2324/fast-das
Classifier: Programming Language :: Python :: 3
Classifier: License :: OSI Approved :: GNU General Public License v2 (GPLv2)
Classifier: Operating System :: OS Independent
Requires-Python: >=3.6
License-File: LICENSE
Requires-Dist: numpy
